torture/__init__.py
torture/enjoy.py
torture/setup.py
torture-0.0.1.dist-info/METADATA
torture-0.0.1.dist-info/WHEEL
torture-0.0.1.dist-info/top_level.txt
torture-0.0.1.dist-info/RECORD
