Metadata-Version: 2.1
Name: torture
Version: 0.0.1
Summary: My first Python package
Author: thepythongoat98
Author-email: ranjanchinmoy@gmail.com
Keywords: python,first package
Classifier: Development Status :: 3 - Alpha
Classifier: Intended Audience :: Education
Classifier: Programming Language :: Python :: 2
Classifier: Programming Language :: Python :: 3
Classifier: Operating System :: MacOS :: MacOS X
Classifier: Operating System :: Microsoft :: Windows
